pysnaptest-0.4.0.dist-info/METADATA
pysnaptest-0.4.0.dist-info/WHEEL
pysnaptest-0.4.0.dist-info/licenses/LICENSE
pysnaptest/__init__.py
pysnaptest/_pysnaptest.cpython-310-x86_64-linux-gnu.so
pysnaptest/assertion.py
pysnaptest/mocks.py
pysnaptest-0.4.0.dist-info/RECORD
