Metadata-Version: 2.4
Name: pysnaptest
Version: 0.4.0
Classifier: Programming Language :: Rust
Classifier: Programming Language :: Python :: Implementation :: CPython
Classifier: Programming Language :: Python :: Implementation :: PyPy
Requires-Dist: pandas>=0.12.0 ; extra == 'pandas'
Requires-Dist: polars>=0.18 ; extra == 'polars'
Requires-Dist: pyarrow>=17.0.0 ; extra == 'pyarrow'
Provides-Extra: pandas
Provides-Extra: polars
Provides-Extra: pyarrow
License-File: LICENSE
Requires-Python: >=3.9
